{
  "x-defs": {
    "ada.bbr.metadata.geochemProperties.stringArray": {
      "title": "String Array Type",
      "description": "Simple reusable array of strings",
      "type": "array",
      "minItems": 0,
      "items": {
        "type": "string"
      },
      "x-schema-source": "https://usgin.github.io/geochemBuildingBlocks/build/annotated/bbr/metadata/geochemProperties/stringArray/schema.json",
      "x-schema-version": "https://json-schema.org/draft/2020-12/schema"
    }
  },
  "title": "NanoIR Instrument Detail",
  "description": "Nano-IR spectroscopy collections with phase analysis",
  "type": "object",
  "properties": {
    "@type": {
      "type": "array",
      "minItems": 1,
      "contains": {
        "anyOf": [
          {
            "enum": [
              "ada:NanoIRBackground"
            ]
          }
        ]
      }
    },
    "ada:phaseAnalyzed": {
      "$ref": "https://usgin.github.io/geochemBuildingBlocks/build/annotated/bbr/metadata/geochemProperties/detailNanoIR/schema-oas3.0.json#/x-defs/ada.bbr.metadata.geochemProperties.stringArray"
    }
  },
  "x-jsonld-prefixes": {
    "schema": "http://schema.org/",
    "ada": "https://ada.astromat.org/metadata/"
  },
  "x-schema-version": "https://json-schema.org/draft/2020-12/schema"
}