{
  "$schema": "metaschema.yaml",
  "name": "Analysis Instrument Type",
  "abstract": "Analytical instrument definition combining NXinstrument and prov:Entity. Defines properties: @type, schema:additionalType, schema:name, schema:description, schema:identifier.",
  "status": "under-development",
  "dateTimeAddition": "2026-02-05T00:00:00Z",
  "itemClass": "schema",
  "register": "cdif-building-block-register",
  "version": "0.1",
  "dateOfLastChange": "2026-02-05",
  "link": "https://github.com/usgin/geochemBuildingBlocks",
  "maturity": "draft",
  "scope": "unstable",
  "tags": [
    "ada",
    "astromat",
    "instrument",
    "provenance"
  ],
  "sources": [
    {
      "title": "ADA Metadata Schema v3",
      "link": "https://github.com/amds-ldeo/metadata"
    }
  ]
}
